pip_rating/__init__.py
pip_rating/_compat.py
pip_rating/dependencies.py
pip_rating/exceptions.py
pip_rating/management.py
pip_rating/packages.py
pip_rating/rating.py
pip_rating/results.py
pip_rating/utils.py
pip_rating/req_files/__init__.py
pip_rating/req_files/base.py
pip_rating/req_files/package_list.py
pip_rating/req_files/pipfile.py
pip_rating/req_files/pyproject.py
pip_rating/req_files/requirements.py
pip_rating/req_files/setupcfg.py
pip_rating/req_files/setuppy.py
pip_rating/sources/__init__.py
pip_rating/sources/audit.py
pip_rating/sources/base.py
pip_rating/sources/pypi.py
pip_rating/sources/sourcecode_page.py
pip_rating/sources/sourcerank.py
pip_rating-0.2.2.dist-info/LICENSE
pip_rating-0.2.2.dist-info/METADATA
pip_rating-0.2.2.dist-info/WHEEL
pip_rating-0.2.2.dist-info/entry_points.txt
pip_rating-0.2.2.dist-info/top_level.txt
pip_rating-0.2.2.dist-info/RECORD
