Metadata-Version: 2.1
Name: pip-rating
Version: 0.2.2
Summary: Check the health of your project's requirements and get a rating for each dependency.
Home-page: https://github.com/Nekmo/pip-rating/
Download-URL: https://github.com/Nekmo/pip-rating/archive/master.zip
Author: Nekmo
Author-email: contacto@nekmo.com
License: MIT license
Keywords: pip-rating
Platform: any
Classifier: Development Status :: 3 - Alpha
Classifier: Programming Language :: Python :: 3 :: Only
Classifier: Programming Language :: Python :: 3.8
Classifier: Programming Language :: Python :: 3.9
Classifier: Programming Language :: Python :: 3.10
Classifier: Programming Language :: Python :: 3.11
Classifier: Programming Language :: Python :: 3.12
Classifier: Operating System :: POSIX :: Linux
Classifier: Operating System :: MacOS :: MacOS X
Classifier: Operating System :: Microsoft :: Windows
Classifier: Operating System :: POSIX :: SunOS/Solaris
Classifier: Operating System :: POSIX :: BSD
Classifier: License :: OSI Approved :: MIT License
Classifier: Natural Language :: English
License-File: LICENSE
Requires-Dist: pipgrip (<0.11.0,>=0.10.0)
Requires-Dist: pip-audit (<3.0.0,>=2.0.0)
Requires-Dist: platformdirs (<4.0.0,>=3.5.1)
Requires-Dist: beautifulsoup4 (<5.0.0,>=4.8.1)
Requires-Dist: setuptools (>=66.1.0)
Requires-Dist: pipfile (<0.1.0,>=0.0.2)
Requires-Dist: requests (<3.0.0,>=2.20.0)
Requires-Dist: rich (>=12.0.0)
Requires-Dist: tomlkit (<1.0.0,>=0.5.1) ; python_version < "3.11"
Requires-Dist: python-dateutil (>=2.8.1) ; python_version < "3.11"
